certbot_plugin_ionos/__init__.py
certbot_plugin_ionos/main.py
certbot_plugin_ionos-0.1.data/data/certbot_plugin_ionos/whl.requirements.txt
certbot_plugin_ionos-0.1.dist-info/METADATA
certbot_plugin_ionos-0.1.dist-info/WHEEL
certbot_plugin_ionos-0.1.dist-info/entry_points.txt
certbot_plugin_ionos-0.1.dist-info/top_level.txt
certbot_plugin_ionos-0.1.dist-info/RECORD
