Metadata-Version: 2.1
Name: certbot-plugin-ionos
Version: 0.1
Summary: Certbot plugin for authentication using the ionos DNS API.
Home-page: https://gitlab.com/todo
Author: Axel Paccalin
Author-email: axel.paccalin@enno.ai
Project-URL: Bug Tracker, https://gitlab.com/todo/issues
Classifier: Programming Language :: Python :: 3
Classifier: Operating System :: OS Independent
Requires-Python: >=3.10
Requires-Dist: certbot
Requires-Dist: ionos-api (==0.1)
